zhtts/__init__.py
zhtts/tts.py
zhtts/asset/baker_mapper.json
zhtts/asset/fastspeech2_quan.tflite
zhtts/asset/mb_melgan.tflite
zhtts/asset/tacotron2_quan.tflite
zhtts/tensorflow_tts/__init__.py
zhtts/tensorflow_tts/processor/__init__.py
zhtts/tensorflow_tts/processor/baker.py
zhtts/tensorflow_tts/processor/base_processor.py
zhtts/tensorflow_tts/processor/cn_tn.py
zhtts-0.0.1.dist-info/LICENSE
zhtts-0.0.1.dist-info/METADATA
zhtts-0.0.1.dist-info/WHEEL
zhtts-0.0.1.dist-info/top_level.txt
zhtts-0.0.1.dist-info/RECORD
