Metadata-Version: 2.1
Name: zhtts
Version: 0.0.1
Summary: A demo of zh/Chinese Text to Speech system run on CPU
Home-page: https://github.com/jackiexiao/zhtts
Author: jackiexiao
Author-email: 707610215@qq.com
License: MIT
Platform: UNKNOWN
Classifier: License :: OSI Approved :: MIT License
Classifier: Programming Language :: Python :: 3.6
Requires-Dist: tensorflow-cpu (>=2.4.0)
Requires-Dist: numpy
Requires-Dist: scipy
Requires-Dist: pypinyin
Requires-Dist: dataclasses
